{"date":"28/10/2020_11:53:34","record":{"agent":"733349405999889999","info":"Load configuration"}}
{"date":"28/10/2020_11:53:34","record":{"agent":"733349405999889999","info":"Found CardID"}}
{"date":"28/10/2020_11:53:34","record":{"agent":"733349405999889999","info":"CardID: gItAiFDZFAAnIA83 which belongs to ROMAN LARROSA LEWANDOWSKA (Cellnex)"}}
{"date":"28/10/2020_11:53:34","record":{"agent":"733349405999889999","info":"Single behaviour agent. Adding plainBehaviour."}}
{"date":"28/10/2020_11:53:34","record":{"agent":"733349405999889999","info":"Trying to checkin in the platform"}}
{"date":"28/10/2020_11:53:34","record":{"agent":"733349405999889999","info":"Requesting checkin to AgentIdentityManager"}}
{"date":"28/10/2020_11:53:34","record":{"agent":"733349405999889999","info":"Chekin confirmed in the platform"}}
{"date":"28/10/2020_11:53:34","record":{"agent":"733349405999889999","info":"Trying to register in LARVA"}}
{"date":"28/10/2020_11:53:34","record":{"agent":"733349405999889999","info":"Found ASSIGNMENTID 2"}}
{"date":"28/10/2020_11:53:34","record":{"agent":"733349405999889999","info":"Retrieving the name of the corresponding LARVA agent for service <Analytics ASSIGNMENTID 2>"}}
{"date":"28/10/2020_11:53:34","record":{"agent":"733349405999889999","info":"LARVA Agent Cellnex found. Requesting registration"}}
{"date":"28/10/2020_11:53:34","record":{"agent":"733349405999889999","info":"\u001b[38;2;0;0;255mSuccesfully registered in LARVA"}}
{"date":"28/10/2020_11:53:34","record":{"agent":"733349405999889999","info":"Behaviour REGULAR starts"}}
{"date":"28/10/2020_11:53:34","record":{"agent":"733349405999889999","info":"Enviando credenciales"}}
{"date":"28/10/2020_11:53:34","record":{"agent":"733349405999889999","info":"Enviada petición de login"}}
{"date":"28/10/2020_11:53:34","record":{"agent":"733349405999889999","info":"******************************************{\"result\":\"ok\",\"key\":\"mnbtmtHS\",\"width\":100,\"height\":100,\"maxflight\":256,\"capabilities\":[\"moveF\",\"rotateL\",\"rotateR\",\"moveUP\",\"moveD\",\"touchD\",\"recharge\",\"rescue\",\"status\",\"trace\",\"alive\",\"distance\",\"altimeter\",\"gps\",\"visual\",\"angular\",\"compass\"]}"}}
{"date":"28/10/2020_11:53:34","record":{"agent":"733349405999889999","info":"La key almacenada es mnbtmtHS"}}
{"date":"28/10/2020_11:53:34","record":{"agent":"733349405999889999","info":"La clave recibida es: mnbtmtHS"}}
{"date":"28/10/2020_11:53:34","record":{"agent":"733349405999889999","info":"El server dice: {\"result\":\"ok\"}"}}
{"date":"28/10/2020_11:53:36","record":{"agent":"733349405999889999","info":"Requesting unregistration in LARVA"}}
{"date":"28/10/2020_11:53:36","record":{"agent":"733349405999889999","info":"Succesfully unregistered in LARVA"}}
{"date":"28/10/2020_11:53:40","record":{"agent":"733349405999889999","info":"Trying to checkout from the platform"}}
{"date":"28/10/2020_11:53:40","record":{"agent":"733349405999889999","info":"Checked-out from the platform"}}
{"date":"28/10/2020_11:53:40","record":{"agent":"733349405999889999","info":"Take down"}}
