{"date":"27/10/2020_18:18:20","record":{"agent":"7333494059988999","info":"Load configuration"}}
{"date":"27/10/2020_18:18:20","record":{"agent":"7333494059988999","info":"Found CardID"}}
{"date":"27/10/2020_18:18:21","record":{"agent":"7333494059988999","info":"CardID: gItAiFDZFAAnIA83 which belongs to ROMAN LARROSA LEWANDOWSKA (Cellnex)"}}
{"date":"27/10/2020_18:18:21","record":{"agent":"7333494059988999","info":"Single behaviour agent. Adding plainBehaviour."}}
{"date":"27/10/2020_18:18:21","record":{"agent":"7333494059988999","info":"Trying to checkin in the platform"}}
{"date":"27/10/2020_18:18:21","record":{"agent":"7333494059988999","info":"Requesting checkin to AgentIdentityManager"}}
{"date":"27/10/2020_18:18:21","record":{"agent":"7333494059988999","info":"Chekin confirmed in the platform"}}
{"date":"27/10/2020_18:18:21","record":{"agent":"7333494059988999","info":"Trying to register in LARVA"}}
{"date":"27/10/2020_18:18:21","record":{"agent":"7333494059988999","info":"Found ASSIGNMENTID 2"}}
{"date":"27/10/2020_18:18:21","record":{"agent":"7333494059988999","info":"Retrieving the name of the corresponding LARVA agent for service <Analytics ASSIGNMENTID 2>"}}
{"date":"27/10/2020_18:18:21","record":{"agent":"7333494059988999","info":"LARVA Agent Cellnex found. Requesting registration"}}
{"date":"27/10/2020_18:18:21","record":{"agent":"7333494059988999","info":"\u001b[38;2;0;0;255mSuccesfully registered in LARVA"}}
{"date":"27/10/2020_18:18:21","record":{"agent":"7333494059988999","info":"Behaviour REGULAR starts"}}
{"date":"27/10/2020_18:18:21","record":{"agent":"7333494059988999","info":"Enviando credenciales"}}
{"date":"27/10/2020_18:18:21","record":{"agent":"7333494059988999","info":"Enviada petición de login"}}
{"date":"27/10/2020_18:18:21","record":{"agent":"7333494059988999","info":"******************************************{\"result\":\"ok\",\"key\":\"6K7IARfL\",\"width\":100,\"height\":100,\"maxflight\":256,\"capabilities\":[\"moveF\",\"rotateL\",\"rotateR\",\"moveUP\",\"moveD\",\"touchD\",\"recharge\",\"rescue\",\"status\",\"trace\",\"alive\",\"distance\",\"altimeter\",\"gps\",\"visual\",\"angular\",\"compass\"]}"}}
{"date":"27/10/2020_18:18:21","record":{"agent":"7333494059988999","info":"La key almacenada es 6K7IARfL"}}
{"date":"27/10/2020_18:18:21","record":{"agent":"7333494059988999","info":"La clave recibida es: 6K7IARfL"}}
{"date":"27/10/2020_18:18:21","record":{"agent":"7333494059988999","info":"El server dice: {\"result\":\"error\",\"details\":\"Action RotateL not within its capabilities\"}"}}
