{"date":"27/10/2020_17:53:31","record":{"agent":"73","info":"Load configuration"}}
{"date":"27/10/2020_17:53:31","record":{"agent":"73","info":"Found CardID"}}
{"date":"27/10/2020_17:53:31","record":{"agent":"73","info":"CardID: gItAiFDZFAAnIA83 which belongs to ROMAN LARROSA LEWANDOWSKA (Cellnex)"}}
{"date":"27/10/2020_17:53:31","record":{"agent":"73","info":"Single behaviour agent. Adding plainBehaviour."}}
{"date":"27/10/2020_17:53:31","record":{"agent":"73","info":"Trying to checkin in the platform"}}
{"date":"27/10/2020_17:53:31","record":{"agent":"73","info":"Requesting checkin to AgentIdentityManager"}}
{"date":"27/10/2020_17:53:31","record":{"agent":"73","info":"Chekin confirmed in the platform"}}
{"date":"27/10/2020_17:53:31","record":{"agent":"73","info":"Trying to register in LARVA"}}
{"date":"27/10/2020_17:53:31","record":{"agent":"73","info":"Found ASSIGNMENTID 2"}}
{"date":"27/10/2020_17:53:31","record":{"agent":"73","info":"Retrieving the name of the corresponding LARVA agent for service <Analytics ASSIGNMENTID 2>"}}
{"date":"27/10/2020_17:53:32","record":{"agent":"73","info":"LARVA Agent Cellnex found. Requesting registration"}}
{"date":"27/10/2020_17:53:32","record":{"agent":"73","info":"\u001b[38;2;0;0;255mSuccesfully registered in LARVA"}}
{"date":"27/10/2020_17:53:32","record":{"agent":"73","info":"Behaviour REGULAR starts"}}
{"date":"27/10/2020_17:53:32","record":{"agent":"73","info":"Enviando credenciales"}}
{"date":"27/10/2020_17:53:32","record":{"agent":"73","info":"Enviada petición de login"}}
{"date":"27/10/2020_17:53:32","record":{"agent":"73","info":"******************************************{\"result\":\"ok\",\"key\":\"048Mi4Lo\",\"width\":100,\"height\":100,\"maxflight\":256,\"capabilities\":[\"moveF\",\"rotateL\",\"rotateR\",\"moveUP\",\"moveD\",\"touchD\",\"recharge\",\"rescue\",\"status\",\"trace\",\"alive\",\"distance\",\"altimeter\",\"gps\",\"visual\"]}"}}
{"date":"27/10/2020_17:53:32","record":{"agent":"73","info":"La key almacenada es 048Mi4Lo"}}
{"date":"27/10/2020_17:53:32","record":{"agent":"73","info":"La clave recibida es: 048Mi4Lo"}}
{"date":"27/10/2020_17:53:32","record":{"agent":"73","info":"El server dice: {\"result\":\"ok\"}"}}
{"date":"27/10/2020_17:53:33","record":{"agent":"73","info":"La lectora de sensores es: {\"result\":\"ok\",\"details\":{\"name\":\"73\",\"perceptions\":[{\"sensor\":\"alive\",\"data\":[1]},{\"sensor\":\"distance\",\"data\":[140.0071426749364]},{\"sensor\":\"altimeter\",\"data\":[0]},{\"sensor\":\"gps\",\"data\":[[99,99,45]]},{\"sensor\":\"visual\",\"data\":[[45,45,45,45,-2147483648,-2147483648,-2147483648],[45,45,45,45,-2147483648,-2147483648,-2147483648],[45,45,45,45,-2147483648,-2147483648,-2147483648],[45,45,45,45,-2147483648,-2147483648,-2147483648],[-2147483648,-2147483648,-2147483648,-2147483648,-2147483648,-2147483648,-2147483648],[-2147483648,-2147483648,-2147483648,-2147483648,-2147483648,-2147483648,-2147483648],[-2147483648,-2147483648,-2147483648,-2147483648,-2147483648,-2147483648,-2147483648]]},{\"sensor\":\"trace\",\"data\":[\"login Playground1\",\"rotateL\"]},{\"sensor\":\"status\",\"data\":[\"\"]}]}}"}}
{"date":"27/10/2020_17:53:33","record":{"agent":"73","info":"Requesting unregistration in LARVA"}}
{"date":"27/10/2020_17:53:33","record":{"agent":"73","info":"Succesfully unregistered in LARVA"}}
{"date":"27/10/2020_17:53:37","record":{"agent":"73","info":"Trying to checkout from the platform"}}
{"date":"27/10/2020_17:53:37","record":{"agent":"73","info":"Checked-out from the platform"}}
{"date":"27/10/2020_17:53:37","record":{"agent":"73","info":"Take down"}}
